JPSL_Tools_Menu/__init__.py
JPSL_Tools_Menu/_version.py
jpsl_tools_menu-0.2.1.data/data/share/jupyter/labextensions/jpsl-tools-menu/package.json
jpsl_tools_menu-0.2.1.data/data/share/jupyter/labextensions/jpsl-tools-menu/static/509.e504687c0da587b86deb.js
jpsl_tools_menu-0.2.1.data/data/share/jupyter/labextensions/jpsl-tools-menu/static/728.800c06a744985c012028.js
jpsl_tools_menu-0.2.1.data/data/share/jupyter/labextensions/jpsl-tools-menu/static/remoteEntry.bd479d7f5d9c8fd5e610.js
jpsl_tools_menu-0.2.1.data/data/share/jupyter/labextensions/jpsl-tools-menu/static/style.js
jpsl_tools_menu-0.2.1.data/data/share/jupyter/labextensions/jpsl-tools-menu/static/third-party-licenses.json
jpsl_tools_menu-0.2.1.data/data/share/jupyter/labextensions/jpsl-tools-menu/install.json
jpsl_tools_menu-0.2.1.dist-info/METADATA
jpsl_tools_menu-0.2.1.dist-info/WHEEL
jpsl_tools_menu-0.2.1.dist-info/licenses/LICENSE
jpsl_tools_menu-0.2.1.dist-info/RECORD
