Metadata-Version: 2.4
Name: JPSL_Tools_Menu
Version: 0.2.1
Dynamic: Keywords
Summary: JLab compatible convenience menu for common activities in Jupyter Physical Science Lab.
Project-URL: Homepage, https://github.com/JupyterPhysSciLab/JPSL_Tools_Menu
Project-URL: Bug Tracker, https://github.com/JupyterPhysSciLab/JPSL_Tools_Menu/issues
Project-URL: Repository, https://github.com/JupyterPhysSciLab/JPSL_Tools_Menu.git
Author-email: Jonathan Gutow <gutow@uwosh.edu>
License: BSD 3-Clause License
License-File: LICENSE
Classifier: Framework :: Jupyter
Classifier: Framework :: Jupyter :: JupyterLab
Classifier: Framework :: Jupyter :: JupyterLab :: 4
Classifier: Framework :: Jupyter :: JupyterLab :: Extensions
Classifier: Framework :: Jupyter :: JupyterLab :: Extensions :: Prebuilt
Classifier: License :: OSI Approved :: BSD License
Classifier: Programming Language :: Python
Classifier: Programming Language :: Python :: 3
Classifier: Programming Language :: Python :: 3.8
Classifier: Programming Language :: Python :: 3.9
Classifier: Programming Language :: Python :: 3.10
Classifier: Programming Language :: Python :: 3.11
Classifier: Programming Language :: Python :: 3.12
Requires-Python: >=3.8
Requires-Dist: algebra-with-sympy
Requires-Dist: jupyter-pandas-gui>=0.9.0
Requires-Dist: jupyterlab<5,>=4.0.0
Requires-Dist: jupyterpidaq>=0.8.1
